poma_senter/__init__.py
poma_senter/cleaner.py
poma_senter/version.py
poma_senter-0.1.2.dist-info/licenses/LICENSE
poma_senter-0.1.2.dist-info/METADATA
poma_senter-0.1.2.dist-info/WHEEL
poma_senter-0.1.2.dist-info/top_level.txt
poma_senter-0.1.2.dist-info/RECORD
