Metadata-Version: 2.4
Name: poma-senter
Version: 0.1.2
Summary: Sentence and line-level text cleaner for .poma and Markdown
Author-email: "TIGON S.L.U." <info@poma.science>
License-Expression: MPL-2.0
Requires-Python: >=3.10
License-File: LICENSE
Dynamic: license-file
